xmlsec.cpython-314-aarch64-linux-musl.so
xmlsec/__init__.pyi
xmlsec/constants.pyi
xmlsec/py.typed
xmlsec/template.pyi
xmlsec/tree.pyi
xmlsec-1.3.17.dist-info/METADATA
xmlsec-1.3.17.dist-info/WHEEL
xmlsec-1.3.17.dist-info/top_level.txt
xmlsec-1.3.17.dist-info/RECORD
xmlsec-1.3.17.dist-info/licenses/LICENSE
