Metadata-Version: 2.4
Name: xmlsec
Version: 1.3.17
Summary: Python bindings for the XML Security Library
Home-page: https://github.com/mehcode/python-xmlsec
Author: Bulat Gaifullin
Author-email: support@mehcode.com
Maintainer: Oleg Hoefling
Maintainer-email: oleg.hoefling@gmail.com
License: MIT
Project-URL: Documentation, https://xmlsec.readthedocs.io
Project-URL: Source, https://github.com/mehcode/python-xmlsec
Project-URL: Changelog, https://github.com/mehcode/python-xmlsec/releases
Keywords: xmlsec
Classifier: Development Status :: 5 - Production/Stable
Classifier: Intended Audience :: Developers
Classifier: Intended Audience :: System Administrators
Classifier: License :: OSI Approved :: MIT License
Classifier: Operating System :: OS Independent
Classifier: Programming Language :: C
Classifier: Programming Language :: Python :: 3
Classifier: Programming Language :: Python :: 3.9
Classifier: Programming Language :: Python :: 3.10
Classifier: Programming Language :: Python :: 3.11
Classifier: Programming Language :: Python :: 3.12
Classifier: Programming Language :: Python :: 3.13
Classifier: Programming Language :: Python :: 3.14
Classifier: Topic :: Text Processing :: Markup :: XML
Classifier: Typing :: Typed
Requires-Python: >=3.9
License-File: LICENSE
Requires-Dist: lxml>=3.8
Dynamic: author
Dynamic: author-email
Dynamic: classifier
Dynamic: description
Dynamic: description-content-type
Dynamic: home-page
Dynamic: keywords
Dynamic: license
Dynamic: license-file
Dynamic: maintainer
Dynamic: maintainer-email
Dynamic: project-url
Dynamic: requires-dist
Dynamic: requires-python
Dynamic: summary
